decorator/__init__.py
decorator/decorator.py
drf_api_decorator/__init__.py
drf_api_decorator/decorator.py
drf_api_decorator-0.0.15.dist-info/METADATA
drf_api_decorator-0.0.15.dist-info/WHEEL
drf_api_decorator-0.0.15.dist-info/top_level.txt
drf_api_decorator-0.0.15.dist-info/RECORD
